sap_utils/__init__.py
sap_utils/context_managers.py
sap_utils/decorators.py
sap_utils/random.py
sap_utils-0.0.3.1.dist-info/METADATA
sap_utils-0.0.3.1.dist-info/WHEEL
sap_utils-0.0.3.1.dist-info/top_level.txt
sap_utils-0.0.3.1.dist-info/RECORD
