Metadata-Version: 2.1
Name: sap-utils
Version: 0.0.3.1
Summary: Random utility code.
Home-page: https://github.com/satyarth934/sap-utils
Author: Satyarth Praveen
Author-email: satyarth934@gmail.com
License: UNKNOWN
Project-URL: Bug Tracker, https://github.com/satyarth934/sap-utils/issues
Project-URL: Source, https://github.com/satyarth934/sap-utils
Platform: UNKNOWN
Classifier: Programming Language :: Python :: 3
Classifier: License :: OSI Approved :: MIT License
Classifier: Operating System :: OS Independent
Requires-Python: >=3.6
Requires-Dist: numpy
Requires-Dist: pandas
Requires-Dist: matplotlib
Requires-Dist: tqdm
Requires-Dist: joblib
